{
	"data":[
	{
		"url":"http://s.weibo.com/weibo/%25E4%25BB%258A%25E5%25B9%25B4%25E9%25AB%2598%25E8%2580%2583%25E6%259C%2589%25E4%25BA%25BA%25E5%259B%25A0%25E8%25BF%259F%25E5%2588%25B02%25E5%2588%2586%25E9%2592%259F%25E8%25A2%25AB%25E6%258B%2592%25E7%25BB%259D%25E8%25BF%259B%25E5%2585%25A5%25E8%2580%2583%25E5%259C%25BA?topnav=1&wvr=6&b=1",
		"board":"新浪微博",
		"title":"温州微博大事小事",
		"content":"#温州身边事# 【今年高考，温州有人因迟到2分钟被拒绝进入考场】9点17分，温州华侨中学考点，护士学校的一位考生因为迟到了2分钟，不能进场考试。据了解，该考生家住龙湾永中，早上6点就出发了，最后仍迟到了2分钟。#2017浙江高考# 秒拍视频",
		"post_time":"2017/6/7 12:26:00"
	}
	],
	"success":true
}